ViolentPythonZhongwenban/README.md
ViolentPythonZhongwenban/__init__.py
ViolentPythonZhongwenban/__main__.py
ViolentPythonZhongwenban/file.epub
ViolentPythonZhongwenban/index.html
ViolentPythonZhongwenban/css/__init__.py
ViolentPythonZhongwenban/css/annotations.css
ViolentPythonZhongwenban/css/main.css
ViolentPythonZhongwenban/css/normalize.css
ViolentPythonZhongwenban/css/popup.css
ViolentPythonZhongwenban/font/__init__.py
ViolentPythonZhongwenban/font/fontello.eot
ViolentPythonZhongwenban/font/fontello.svg
ViolentPythonZhongwenban/font/fontello.ttf
ViolentPythonZhongwenban/font/fontello.woff
ViolentPythonZhongwenban/img/__init__.py
ViolentPythonZhongwenban/img/annotator-glyph-sprite.png
ViolentPythonZhongwenban/img/annotator-icon-sprite.png
ViolentPythonZhongwenban/img/apple-touch-icon.png
ViolentPythonZhongwenban/img/cancelfullscreen.png
ViolentPythonZhongwenban/img/close.png
ViolentPythonZhongwenban/img/fullscreen.png
ViolentPythonZhongwenban/img/loader.gif
ViolentPythonZhongwenban/img/menu-icon.png
ViolentPythonZhongwenban/img/save.png
ViolentPythonZhongwenban/img/saved.png
ViolentPythonZhongwenban/img/settings-s.png
ViolentPythonZhongwenban/img/settings.png
ViolentPythonZhongwenban/img/star.png
ViolentPythonZhongwenban/js/__init__.py
ViolentPythonZhongwenban/js/epub.js
ViolentPythonZhongwenban/js/epub.min.js
ViolentPythonZhongwenban/js/epub.min.map
ViolentPythonZhongwenban/js/hooks.min.js
ViolentPythonZhongwenban/js/hooks.min.map
ViolentPythonZhongwenban/js/reader.js
ViolentPythonZhongwenban/js/reader.js.map
ViolentPythonZhongwenban/js/reader.min.js
ViolentPythonZhongwenban/js/reader.min.map
ViolentPythonZhongwenban/js/hooks/__init__.py
ViolentPythonZhongwenban/js/hooks/extensions/__init__.py
ViolentPythonZhongwenban/js/hooks/extensions/highlight.js
ViolentPythonZhongwenban/js/libs/__init__.py
ViolentPythonZhongwenban/js/libs/jquery.min.js
ViolentPythonZhongwenban/js/libs/localforage.min.js
ViolentPythonZhongwenban/js/libs/screenfull.js
violent_python_zhongwenban-2024.3.2.0.dist-info/METADATA
violent_python_zhongwenban-2024.3.2.0.dist-info/WHEEL
violent_python_zhongwenban-2024.3.2.0.dist-info/entry_points.txt
violent_python_zhongwenban-2024.3.2.0.dist-info/top_level.txt
violent_python_zhongwenban-2024.3.2.0.dist-info/RECORD
